MANIFEST.in
README.rst
setup.cfg
setup.py
jdsuocm/__init__.py
jdsuocm/device.py
jdsuocm/error.py
jdsuocm/main.py
jdsuocm/scan.py
jdsuocm/sercat.py
jdsuocm/server.py
jdsuocm.egg-info/PKG-INFO
jdsuocm.egg-info/SOURCES.txt
jdsuocm.egg-info/dependency_links.txt
jdsuocm.egg-info/entry_points.txt
jdsuocm.egg-info/requires.txt
jdsuocm.egg-info/top_level.txt