Metadata-Version: 1.0
Name: jdsuocm
Version: 0.2.0
Summary: JDSU OCM
Home-page: https://github.com/choppsv1/jdsu-ocm
Author: Christian E. Hopps
Author-email: chopps@gmail.com
License: Apache License, Version 2.0
Platform: UNKNOWN
